README.rst
bon_csvAvg.py
setup.py
bon_csvAvg.egg-info/PKG-INFO
bon_csvAvg.egg-info/SOURCES.txt
bon_csvAvg.egg-info/dependency_links.txt
bon_csvAvg.egg-info/top_level.txt