Metadata-Version: 1.1
Name: bon-csvAvg
Version: 0.2
Summary: calculate the average of a number of bonnie++ test
Home-page: https://github.com/jayme-github/bon_csvAvg
Author: Jayme
Author-email: tuxnet@gmail.com
License: GNU Affero General Public License v3
Keywords: bonnie
Platform: any
Classifier: Development Status :: 4 - Beta
Classifier: Intended Audience :: System Administrators
Classifier: License :: OSI Approved :: GNU Affero General Public License v3
Classifier: Operating System :: OS Independent
Classifier: Programming Language :: Python :: 3
